setup.py
cocoa_packer.egg-info/PKG-INFO
cocoa_packer.egg-info/SOURCES.txt
cocoa_packer.egg-info/dependency_links.txt
cocoa_packer.egg-info/entry_points.txt
cocoa_packer.egg-info/top_level.txt
package/__init__.py
package/cocoa_package.py
package/pick.py