Metadata-Version: 1.1
Name: cocoa-packer
Version: 1.8.3
Summary: A cocoapods package packer
Home-page: https://github.com/zhipengbird/cocoapodsPackage
Author: yuanpinghua
Author-email: yuanpinghua@yeah.net
License: MIT
Keywords: cocoapods  package
Platform: UNKNOWN
Classifier: Development Status :: 4 - Beta
Classifier: Intended Audience :: Developers
Classifier: License :: OSI Approved :: MIT License
Classifier: Programming Language :: Python
Classifier: Programming Language :: Python :: 2.6
Classifier: Programming Language :: Python :: 2.7
